[
  {
    "id": "1eec5a82-7798-641d-a077-57b230fd1b19",
    "transaction_code": "T33K944L4V",
    "status": "SUCCESSFUL",
    "timestamp": "2024-02-07T11:00:50.290Z",
    "type": "PAYMENT",
    "amount": 7.5,
    "simple_status": "PAID_OUT",
    "t_status": "SUCCESSFUL",
    "t_timestamp": "2024-02-07T11:00:50.290Z",
    "client_transaction_id": "B8A680A1-4842-4E7B-B7E6-C92366C4B473-274-00000026EAF00786",
    "fee_amount": 0.07,
    "t_card": "VISA",
    "refunded_amount": 0
  },
  {
    "id": "1eec5a96-c540-655a-8c71-378c61f2bc0d",
    "transaction_code": "TMFKK4VNL4",
    "status": "SUCCESSFUL",
    "timestamp": "2024-02-07T11:09:55.304Z",
    "type": "PAYMENT",
    "amount": 3.55,
    "simple_status": "PAID_OUT",
    "t_status": "SUCCESSFUL",
    "t_timestamp": "2024-02-07T11:09:55.304Z",
    "client_transaction_id": "C1C7964C-B80B-4FEE-95B4-24E2322FA6DB-274-00000029F6CD70D8",
    "fee_amount": 0.04,
    "t_card": "MASTERCARD",
    "refunded_amount": 0
  },
  {
    "id": "1eec5a9d-04d2-60d5-81c8-a67430df5961",
    "transaction_code": "TDVDTYFEYN",
    "status": "SUCCESSFUL",
    "timestamp": "2024-02-07T11:12:43.034Z",
    "type": "PAYMENT",
    "amount": 2.5,
    "simple_status": "PAID_OUT",
    "t_status": "SUCCESSFUL",
    "t_timestamp": "2024-02-07T11:12:43.034Z",
    "client_transaction_id": "97A58159-34BD-40D1-B3A3-C8836C18CBBF-274-0000002AE6D00D48",
    "fee_amount": 0.02,
    "t_card": "MASTERCARD",
    "refunded_amount": 0
  },
  {
    "id": "1eec5aaa-22a9-60a8-bb43-5f0cec53fda2",
    "transaction_code": "TYT29LPN6S",
    "status": "SUCCESSFUL",
    "timestamp": "2024-02-07T11:18:35.133Z",
    "type": "PAYMENT",
    "amount": 4.75,
    "simple_status": "PAID_OUT",
    "t_status": "SUCCESSFUL",
    "t_timestamp": "2024-02-07T11:18:35.133Z",
    "client_transaction_id": "BFF9E6E6-7A0C-4AD6-8CA2-1F6576D637C0-274-0000002CDE6FB0CE",
    "fee_amount": 0.05,
    "t_card": "VISA",
    "refunded_amount": 0
  },
  {
    "id": "1eec5abc-52b0-677f-b1cc-2386a32fdc9e",
    "transaction_code": "TC6HKK7LH3",
    "status": "SUCCESSFUL",
    "timestamp": "2024-02-07T11:26:43.347Z",
    "type": "PAYMENT",
    "amount": 3,
    "simple_status": "PAID_OUT",
    "t_status": "SUCCESSFUL",
    "t_timestamp": "2024-02-07T11:26:43.347Z",
    "client_transaction_id": "CF07AB7E-2EC4-41E0-948A-267ED0AFF4C7-274-0000002F98E0027D",
    "fee_amount": 0.03,
    "t_card": "MASTERCARD",
    "refunded_amount": 0
  },
  {
    "id": "1eec5abe-83c7-616f-a1ee-84536cad7984",
    "transaction_code": "TEM73Z3UD4",
    "status": "SUCCESSFUL",
    "timestamp": "2024-02-07T11:27:42.182Z",
    "type": "PAYMENT",
    "amount": 1.75,
    "simple_status": "PAID_OUT",
    "t_status": "SUCCESSFUL",
    "t_timestamp": "2024-02-07T11:27:42.182Z",
    "client_transaction_id": "8E158F3D-F0A8-4565-9D65-D3DDBE2A2639-274-0000002FED0DB02B",
    "fee_amount": 0.02,
    "t_card": "VISA",
    "refunded_amount": 0
  },
  {
    "id": "1eec5ac0-4273-692c-956e-f4143f5c01bb",
    "transaction_code": "TEV3KHZQSV",
    "status": "SUCCESSFUL",
    "timestamp": "2024-02-07T11:28:29.020Z",
    "type": "PAYMENT",
    "amount": 2.42,
    "simple_status": "PAID_OUT",
    "t_status": "SUCCESSFUL",
    "t_timestamp": "2024-02-07T11:28:29.020Z",
    "client_transaction_id": "B60EC897-67A5-4269-AFAC-7CA9B57FA713-274-000000302FF8A584",
    "fee_amount": 0.02,
    "t_card": "VISA",
    "refunded_amount": 0
  },
  {
    "id": "1eec5afb-e16e-6111-a4d9-8c787341e093",
    "transaction_code": "TDV7C2LZG9",
    "status": "SUCCESSFUL",
    "timestamp": "2024-02-07T11:55:09.455Z",
    "type": "PAYMENT",
    "amount": 5.17,
    "simple_status": "PAID_OUT",
    "t_status": "SUCCESSFUL",
    "t_timestamp": "2024-02-07T11:55:09.455Z",
    "client_transaction_id": "9EFAAAE7-8849-4AA8-8248-97F019543872-377-00000841872CD0EB",
    "fee_amount": 0.05,
    "t_card": "MASTERCARD",
    "refunded_amount": 0
  },
  {
    "id": "1eec5b03-fc45-6edd-a140-68a6b062a558",
    "transaction_code": "TCP49YYUNP",
    "status": "SUCCESSFUL",
    "timestamp": "2024-02-07T11:58:47.023Z",
    "type": "PAYMENT",
    "amount": 12.24,
    "simple_status": "PAID_OUT",
    "t_status": "SUCCESSFUL",
    "t_timestamp": "2024-02-07T11:58:47.023Z",
    "client_transaction_id": "5111D200-A007-41AC-9D45-15B0664CD6C0-377-00000842BE6E7A71",
    "fee_amount": 0.12,
    "t_card": "MASTERCARD",
    "refunded_amount": 0
  },
  {
    "id": "1eec5b0d-cacc-640a-a3dc-ddff28012799",
    "transaction_code": "TE23PKCC3M",
    "status": "SUCCESSFUL",
    "timestamp": "2024-02-07T12:03:10.274Z",
    "type": "PAYMENT",
    "amount": 3,
    "simple_status": "PAID_OUT",
    "t_status": "SUCCESSFUL",
    "t_timestamp": "2024-02-07T12:03:10.274Z",
    "client_transaction_id": "931B8DDB-728A-45A7-8713-B5C70626B887-274-0000003BD11A70CA",
    "fee_amount": 0.03,
    "t_card": "MASTERCARD",
    "refunded_amount": 0
  },
  {
    "id": "1eec5c11-0389-67d5-bfeb-450a34f918b4",
    "transaction_code": "TD3XLFEVNQ",
    "status": "SUCCESSFUL",
    "timestamp": "2024-02-07T13:59:08.714Z",
    "type": "PAYMENT",
    "amount": 10.17,
    "simple_status": "PAID_OUT",
    "t_status": "SUCCESSFUL",
    "t_timestamp": "2024-02-07T13:59:08.714Z",
    "client_transaction_id": "438EDEC4-AECC-4078-B3D4-60F5687E9E3B-274-00000062B402970C",
    "fee_amount": 0.1,
    "t_card": "MASTERCARD",
    "refunded_amount": 0
  },
  {
    "id": "1eec5c14-3685-61dc-a10e-0049018c244e",
    "transaction_code": "TCVVKVKR2L",
    "status": "SUCCESSFUL",
    "timestamp": "2024-02-07T14:00:34.573Z",
    "type": "PAYMENT",
    "amount": 5.1,
    "simple_status": "PAID_OUT",
    "t_status": "SUCCESSFUL",
    "t_timestamp": "2024-02-07T14:00:34.573Z",
    "client_transaction_id": "20D3BA12-5C07-487A-B0C9-89F361379E63-274-000000632EED9EA0",
    "fee_amount": 0.05,
    "t_card": "VISA",
    "refunded_amount": 0
  },
  {
    "id": "1eec5c20-969f-679d-8405-723eaace1ffe",
    "transaction_code": "TDFNVRZCFZ",
    "status": "SUCCESSFUL",
    "timestamp": "2024-02-07T14:06:06.769Z",
    "type": "PAYMENT",
    "amount": 4.5,
    "simple_status": "PAID_OUT",
    "t_status": "SUCCESSFUL",
    "t_timestamp": "2024-02-07T14:06:06.769Z",
    "client_transaction_id": "39F4EB46-4460-4FBD-8EE2-8CB22EE53B3D-274-000000650A1740BD",
    "fee_amount": 0.04,
    "t_card": "MASTERCARD",
    "refunded_amount": 0
  },
  {
    "id": "1eec5c21-f923-6bd6-908d-722c4c9ce738",
    "transaction_code": "TDKF393VSH",
    "status": "SUCCESSFUL",
    "timestamp": "2024-02-07T14:06:43.952Z",
    "type": "PAYMENT",
    "amount": 3.5,
    "simple_status": "PAID_OUT",
    "t_status": "SUCCESSFUL",
    "t_timestamp": "2024-02-07T14:06:43.952Z",
    "client_transaction_id": "37D10AD9-8821-4252-AF79-BA1C92C1FCA6-274-000000653F72B50C",
    "fee_amount": 0.03,
    "t_card": "MASTERCARD",
    "refunded_amount": 0
  },
  {
    "id": "1eec5c25-87c5-6d64-895a-a6e3ff5667f7",
    "transaction_code": "TDYKC92KXD",
    "status": "SUCCESSFUL",
    "timestamp": "2024-02-07T14:08:19.439Z",
    "type": "PAYMENT",
    "amount": 6.1,
    "simple_status": "PAID_OUT",
    "t_status": "SUCCESSFUL",
    "t_timestamp": "2024-02-07T14:08:19.439Z",
    "client_transaction_id": "1EEAA4FA-A919-4224-B7BE-753AF1BA1872-274-00000065C7FDEE7B",
    "fee_amount": 0.06,
    "t_card": "MASTERCARD",
    "refunded_amount": 0
  },
  {
    "id": "1eec5c2d-4b2b-624c-8abc-d6666d8bfa67",
    "transaction_code": "TDGRPNSMHD",
    "status": "SUCCESSFUL",
    "timestamp": "2024-02-07T14:11:47.824Z",
    "type": "PAYMENT",
    "amount": 5.17,
    "simple_status": "PAID_OUT",
    "t_status": "SUCCESSFUL",
    "t_timestamp": "2024-02-07T14:11:47.824Z",
    "client_transaction_id": "B988AF44-B4E1-470F-8BDD-7871ABE00149-274-00000066F216CD68",
    "fee_amount": 0.05,
    "t_card": "MASTERCARD",
    "refunded_amount": 0
  },
  {
    "id": "1eec5c2f-1058-614d-abdb-cda12b204e81",
    "transaction_code": "TEFQZELMA2",
    "status": "SUCCESSFUL",
    "timestamp": "2024-02-07T14:12:35.346Z",
    "type": "PAYMENT",
    "amount": 5.4,
    "simple_status": "PAID_OUT",
    "t_status": "SUCCESSFUL",
    "t_timestamp": "2024-02-07T14:12:35.346Z",
    "client_transaction_id": "FCFF7E6A-BCD2-4882-9429-92EF3A42CC06-274-00000067361BF8DC",
    "fee_amount": 0.05,
    "t_card": "VISA",
    "refunded_amount": 0
  },
  {
    "id": "1eec5c38-be38-67f6-8c20-1586a86c28db",
    "transaction_code": "TCPPH4FPUE",
    "status": "SUCCESSFUL",
    "timestamp": "2024-02-07T14:16:55.164Z",
    "type": "PAYMENT",
    "amount": 4.75,
    "simple_status": "PAID_OUT",
    "t_status": "SUCCESSFUL",
    "t_timestamp": "2024-02-07T14:16:55.164Z",
    "client_transaction_id": "95C07733-DA72-412D-ADCD-F36CB30EE48A-274-00000068A9CEBB93",
    "fee_amount": 0.05,
    "t_card": "MASTERCARD",
    "refunded_amount": 0
  },
  {
    "id": "1eec5c3c-68da-640f-9a2c-3414f7d33409",
    "transaction_code": "TDAEC9R9RA",
    "status": "SUCCESSFUL",
    "timestamp": "2024-02-07T14:18:33.583Z",
    "type": "PAYMENT",
    "amount": 10.2,
    "simple_status": "PAID_OUT",
    "t_status": "SUCCESSFUL",
    "t_timestamp": "2024-02-07T14:18:33.583Z",
    "client_transaction_id": "A8EE8C78-7739-442D-8521-3BA0F96B9597-274-00000069368975BB",
    "fee_amount": 0.1,
    "t_card": "VISA",
    "refunded_amount": 0
  },
  {
    "id": "1eec5c3e-abdf-64bd-9351-49ef7a55f1da",
    "transaction_code": "TFKGUDR6UZ",
    "status": "SUCCESSFUL",
    "timestamp": "2024-02-07T14:19:34.366Z",
    "type": "PAYMENT",
    "amount": 4.33,
    "simple_status": "PAID_OUT",
    "t_status": "SUCCESSFUL",
    "t_timestamp": "2024-02-07T14:19:34.366Z",
    "client_transaction_id": "4CFF120A-64B7-4887-89B7-D16BCD3F9FC5-274-000000698D83865E",
    "fee_amount": 0.04,
    "t_card": "VISA",
    "refunded_amount": 0
  },
  {
    "id": "1eec5c43-4bfd-6ff7-b949-b7a204892e07",
    "transaction_code": "TC3UUYVML6",
    "status": "SUCCESSFUL",
    "timestamp": "2024-02-07T14:21:38.473Z",
    "type": "PAYMENT",
    "amount": 4.75,
    "simple_status": "PAID_OUT",
    "t_status": "SUCCESSFUL",
    "t_timestamp": "2024-02-07T14:21:38.473Z",
    "client_transaction_id": "D7B8997C-F12C-418D-AE9E-8B5BC9B40469-274-0000006A3F157398",
    "fee_amount": 0.05,
    "t_card": "MASTERCARD",
    "refunded_amount": 0
  },
  {
    "id": "1eec5c47-a4ab-68bf-87fb-1a3f77ec6ffa",
    "transaction_code": "TDCY3EQMRH",
    "status": "SUCCESSFUL",
    "timestamp": "2024-02-07T14:23:35.135Z",
    "type": "PAYMENT",
    "amount": 11.1,
    "simple_status": "PAID_OUT",
    "t_status": "SUCCESSFUL",
    "t_timestamp": "2024-02-07T14:23:35.135Z",
    "client_transaction_id": "545DE62E-2A74-447C-935D-B2C1B698A9AC-274-0000006AE5FDDA3B",
    "fee_amount": 0.11,
    "t_card": "VISA",
    "refunded_amount": 0
  },
  {
    "id": "1eec5c4e-afb0-61e8-b0de-1ef84f499e5a",
    "transaction_code": "TCHHD6Q293",
    "status": "SUCCESSFUL",
    "timestamp": "2024-02-07T14:26:44.195Z",
    "type": "PAYMENT",
    "amount": 1,
    "simple_status": "PAID_OUT",
    "t_status": "SUCCESSFUL",
    "t_timestamp": "2024-02-07T14:26:44.195Z",
    "client_transaction_id": "8A0EB445-7B73-461B-B4DA-0DAE70C01DEB-274-0000006BF46969BD",
    "fee_amount": 0.01,
    "t_card": "MASTERCARD",
    "refunded_amount": 0
  },
  {
    "id": "1eec5c60-729f-6f5a-a130-115a7643a15b",
    "transaction_code": "TFQGFKNH7D",
    "status": "SUCCESSFUL",
    "timestamp": "2024-02-07T14:34:40.980Z",
    "type": "PAYMENT",
    "amount": 4.05,
    "simple_status": "PAID_OUT",
    "t_status": "SUCCESSFUL",
    "t_timestamp": "2024-02-07T14:34:40.980Z",
    "client_transaction_id": "25A8764A-43D4-41EE-A8A0-8D90234456A6-274-0000006E9E7D47F3",
    "fee_amount": 0.04,
    "t_card": "MASTERCARD",
    "refunded_amount": 0
  },
  {
    "id": "1eec5c8b-df6b-61f1-bb85-d37ce0117329",
    "transaction_code": "TD26MZM9RM",
    "status": "SUCCESSFUL",
    "timestamp": "2024-02-07T14:54:06.749Z",
    "type": "PAYMENT",
    "amount": 1.75,
    "simple_status": "PAID_OUT",
    "t_status": "SUCCESSFUL",
    "t_timestamp": "2024-02-07T14:54:06.749Z",
    "client_transaction_id": "13E09C60-1EE1-4968-90DC-B30E22FF3AD0-274-000000752211A136",
    "fee_amount": 0.02,
    "t_card": "MASTERCARD",
    "refunded_amount": 0
  },
  {
    "id": "1eec5d40-415e-6e87-8f0f-fc6c23d22cab",
    "transaction_code": "TEMXSUQ9GG",
    "status": "SUCCESSFUL",
    "timestamp": "2024-02-07T16:14:48.778Z",
    "type": "PAYMENT",
    "amount": 8.54,
    "simple_status": "PAID_OUT",
    "t_status": "SUCCESSFUL",
    "t_timestamp": "2024-02-07T16:14:48.778Z",
    "client_transaction_id": "419898A4-5CE1-4841-A74C-422EF0118D01-274-00000090310B6E41",
    "fee_amount": 0.08,
    "t_card": "VISA",
    "refunded_amount": 0
  },
  {
    "id": "1eec5d47-169f-6df6-9cf6-006591fc3e63",
    "transaction_code": "TES9F7YGTP",
    "status": "SUCCESSFUL",
    "timestamp": "2024-02-07T16:17:52.202Z",
    "type": "PAYMENT",
    "amount": 5.06,
    "simple_status": "PAID_OUT",
    "t_status": "SUCCESSFUL",
    "t_timestamp": "2024-02-07T16:17:52.202Z",
    "client_transaction_id": "29685256-68E6-4002-BE5D-52C19ADE5EB1-274-000000913782E448",
    "fee_amount": 0.05,
    "t_card": "VISA",
    "refunded_amount": 0
  },
  {
    "id": "1eec5d4f-e5bf-694b-87b7-05633006456b",
    "transaction_code": "TUAH9FEC2Z",
    "status": "SUCCESSFUL",
    "timestamp": "2024-02-07T16:21:48.706Z",
    "type": "PAYMENT",
    "amount": 4.21,
    "simple_status": "PAID_OUT",
    "t_status": "SUCCESSFUL",
    "t_timestamp": "2024-02-07T16:21:48.706Z",
    "client_transaction_id": "0F0C8E17-848D-4970-9DE6-EAAFEFE9B16E-274-0000009289D57F87",
    "fee_amount": 0.04,
    "t_card": "VISA",
    "refunded_amount": 0
  },
  {
    "id": "1eec5d69-4f7f-6de9-af21-4453ab1879ae",
    "transaction_code": "TFS34C24ML",
    "status": "SUCCESSFUL",
    "timestamp": "2024-02-07T16:33:10.838Z",
    "type": "PAYMENT",
    "amount": 17.81,
    "simple_status": "PAID_OUT",
    "t_status": "SUCCESSFUL",
    "t_timestamp": "2024-02-07T16:33:10.838Z",
    "client_transaction_id": "B8A10C38-A0C4-4BCF-9DB8-968A4478A2C0-274-0000009659B618BC",
    "fee_amount": 0.18,
    "t_card": "VISA",
    "refunded_amount": 0
  },
  {
    "id": "1eec5d98-618c-62c7-b36a-61e3f8b29688",
    "transaction_code": "TCELQ24NL9",
    "status": "SUCCESSFUL",
    "timestamp": "2024-02-07T16:54:14.385Z",
    "type": "PAYMENT",
    "amount": 6.38,
    "simple_status": "PAID_OUT",
    "t_status": "SUCCESSFUL",
    "t_timestamp": "2024-02-07T16:54:14.385Z",
    "client_transaction_id": "1E9D27BB-5852-4B0B-BA9C-3CCCF2909A27-274-0000009D695719AE",
    "fee_amount": 0.06,
    "t_card": "MASTERCARD",
    "refunded_amount": 0
  },
  {
    "id": "1eec5e33-e016-6cd7-8544-0a80a2ffdd55",
    "transaction_code": "TD2P9QTK4M",
    "status": "SUCCESSFUL",
    "timestamp": "2024-02-07T18:03:48.436Z",
    "type": "PAYMENT",
    "amount": 15.12,
    "simple_status": "PAID_OUT",
    "t_status": "SUCCESSFUL",
    "t_timestamp": "2024-02-07T18:03:48.436Z",
    "client_transaction_id": "86665B7D-B111-4158-B485-FD2A856564DD-274-000000B4BC9B919F",
    "fee_amount": 0.15,
    "t_card": "MASTERCARD",
    "refunded_amount": 0
  },
  {
    "id": "1eec5e55-34cb-64d1-9ff4-8c28f1fb5bd2",
    "transaction_code": "TC7ZZR3GFK",
    "status": "SUCCESSFUL",
    "timestamp": "2024-02-07T18:18:43.112Z",
    "type": "PAYMENT",
    "amount": 6.07,
    "simple_status": "PAID_OUT",
    "t_status": "SUCCESSFUL",
    "t_timestamp": "2024-02-07T18:18:43.112Z",
    "client_transaction_id": "02878F39-BFAE-4B47-9C91-7897565E0985-274-000000B9BC954B93",
    "fee_amount": 0.06,
    "t_card": "MASTERCARD",
    "refunded_amount": 0
  },
  {
    "id": "1eec5e85-e7a7-6227-8747-aed5d04ccbfe",
    "transaction_code": "TDN3CCQUM9",
    "status": "SUCCESSFUL",
    "timestamp": "2024-02-07T18:40:30.361Z",
    "type": "PAYMENT",
    "amount": 11.6,
    "simple_status": "PAID_OUT",
    "t_status": "SUCCESSFUL",
    "t_timestamp": "2024-02-07T18:40:30.361Z",
    "client_transaction_id": "26CF0580-E02E-4B65-8C49-018721E6BD3B-274-000000C10AB1999E",
    "fee_amount": 0.11,
    "t_card": "MASTERCARD",
    "refunded_amount": 0
  },
  {
    "id": "1eec5e8c-ece7-66a7-b30c-c18daabb27f0",
    "transaction_code": "TDR9HHQ6LC",
    "status": "SUCCESSFUL",
    "timestamp": "2024-02-07T18:43:38.813Z",
    "type": "PAYMENT",
    "amount": 8.41,
    "simple_status": "PAID_OUT",
    "t_status": "SUCCESSFUL",
    "t_timestamp": "2024-02-07T18:43:38.813Z",
    "client_transaction_id": "7FCD72B3-CB59-4991-BA94-E43D55F73008-274-000000C218470169",
    "fee_amount": 0.08,
    "t_card": "VISA",
    "refunded_amount": 0
  },
  {
    "id": "1eec5ea0-16fc-686a-ba25-0146a074e2ce",
    "transaction_code": "TCFDTSTXV6",
    "status": "SUCCESSFUL",
    "timestamp": "2024-02-07T18:52:13.265Z",
    "type": "PAYMENT",
    "amount": 5.17,
    "simple_status": "PAID_OUT",
    "t_status": "SUCCESSFUL",
    "t_timestamp": "2024-02-07T18:52:13.265Z",
    "client_transaction_id": "D8A5DAB7-8D20-4D07-AFAA-E8D4CC40981C-274-000000C4F83D968C",
    "fee_amount": 0.05,
    "t_card": "VISA",
    "refunded_amount": 0
  },
  {
    "id": "1eec5eca-cea5-6dcb-be42-daabbb996e3f",
    "transaction_code": "TD4GZ6P3H4",
    "status": "SUCCESSFUL",
    "timestamp": "2024-02-07T19:11:19.943Z",
    "type": "PAYMENT",
    "amount": 26.96,
    "simple_status": "PAID_OUT",
    "t_status": "SUCCESSFUL",
    "t_timestamp": "2024-02-07T19:11:19.943Z",
    "client_transaction_id": "93F5EBC0-AD9F-498A-B7B4-9B0B81F4B5D6-274-000000CB60AC069A",
    "fee_amount": 0.27,
    "t_card": "VISA",
    "refunded_amount": 0
  },
  {
    "id": "1eec5ecf-de49-69df-bd89-b69749e38f88",
    "transaction_code": "TC9CFTUXAG",
    "status": "SUCCESSFUL",
    "timestamp": "2024-02-07T19:13:35.800Z",
    "type": "PAYMENT",
    "amount": 13.3,
    "simple_status": "PAID_OUT",
    "t_status": "SUCCESSFUL",
    "t_timestamp": "2024-02-07T19:13:35.800Z",
    "client_transaction_id": "396F386F-C31D-4BBA-A43E-ADF1C12A54E0-274-000000CC2314BC32",
    "fee_amount": 0.13,
    "t_card": "VISA",
    "refunded_amount": 0
  },
  {
    "id": "1eec5ed2-bd4a-607a-b44e-9d093e0754e2",
    "transaction_code": "TCQSA3H2TV",
    "status": "SUCCESSFUL",
    "timestamp": "2024-02-07T19:14:52.875Z",
    "type": "PAYMENT",
    "amount": 8.42,
    "simple_status": "PAID_OUT",
    "t_status": "SUCCESSFUL",
    "t_timestamp": "2024-02-07T19:14:52.875Z",
    "client_transaction_id": "3841FA4C-01A9-4D4E-A7AF-DCC3D54E2CC1-274-000000CC916A10BB",
    "fee_amount": 0.08,
    "t_card": "VISA",
    "refunded_amount": 0
  },
  {
    "id": "1eec5ed3-e13a-6a35-b470-50102465e065",
    "transaction_code": "TE6DP3HANM",
    "status": "SUCCESSFUL",
    "timestamp": "2024-02-07T19:15:23.487Z",
    "type": "PAYMENT",
    "amount": 9.95,
    "simple_status": "PAID_OUT",
    "t_status": "SUCCESSFUL",
    "t_timestamp": "2024-02-07T19:15:23.487Z",
    "client_transaction_id": "C517E354-6030-45FE-9D70-58166C795DBC-274-000000CCBD37111A",
    "fee_amount": 0.1,
    "t_card": "VISA",
    "refunded_amount": 0
  },
  {
    "id": "1eec5edd-c784-692d-bb59-1a988546f2b7",
    "transaction_code": "TCVZQUPFSX",
    "status": "SUCCESSFUL",
    "timestamp": "2024-02-07T19:19:49.224Z",
    "type": "PAYMENT",
    "amount": 4.59,
    "simple_status": "PAID_OUT",
    "t_status": "SUCCESSFUL",
    "t_timestamp": "2024-02-07T19:19:49.224Z",
    "client_transaction_id": "D5D6E432-8CA3-4824-ADDE-919AE3A65B58-274-000000CE3948E3EE",
    "fee_amount": 0.05,
    "t_card": "VISA",
    "refunded_amount": 0
  },
  {
    "id": "1eec5ef0-30d3-6075-b176-a3b4ce8cf918",
    "transaction_code": "TFNQXKLG7N",
    "status": "SUCCESSFUL",
    "timestamp": "2024-02-07T19:28:03.444Z",
    "type": "PAYMENT",
    "amount": 5.1,
    "simple_status": "PAID_OUT",
    "t_status": "SUCCESSFUL",
    "t_timestamp": "2024-02-07T19:28:03.444Z",
    "client_transaction_id": "D7DE9AFB-BBC9-4B96-9888-E2CC7B4CC83A-274-000000D0FC644D9C",
    "fee_amount": 0.05,
    "t_card": "VISA",
    "refunded_amount": 0
  },
  {
    "id": "1eec5ef2-aedd-65f3-ab8e-92f06c61b3ae",
    "transaction_code": "TFA4ZAY36F",
    "status": "SUCCESSFUL",
    "timestamp": "2024-02-07T19:29:10.349Z",
    "type": "PAYMENT",
    "amount": 4.39,
    "simple_status": "PAID_OUT",
    "t_status": "SUCCESSFUL",
    "t_timestamp": "2024-02-07T19:29:10.349Z",
    "client_transaction_id": "F68F4117-BA70-4F2C-A219-C8F3A01EB21E-274-000000D15BF18BB0",
    "fee_amount": 0.04,
    "t_card": "MASTERCARD",
    "refunded_amount": 0
  },
  {
    "id": "1eec5f15-d559-6176-be67-0dc2da08ff1b",
    "transaction_code": "TDYFL3KG4P",
    "status": "SUCCESSFUL",
    "timestamp": "2024-02-07T19:44:53.907Z",
    "type": "PAYMENT",
    "amount": 2.69,
    "simple_status": "PAID_OUT",
    "t_status": "SUCCESSFUL",
    "t_timestamp": "2024-02-07T19:44:53.907Z",
    "client_transaction_id": "6DE84423-FEA1-4C67-AC8E-05B841CC157D-274-000000D6A1CA48FD",
    "fee_amount": 0.03,
    "t_card": "MASTERCARD",
    "refunded_amount": 0
  },
  {
    "id": "1eec5f1c-b642-60d0-9a3d-cdef9105a7c7",
    "transaction_code": "TERHXZM2YE",
    "status": "SUCCESSFUL",
    "timestamp": "2024-02-07T19:47:58.576Z",
    "type": "PAYMENT",
    "amount": 4.39,
    "simple_status": "PAID_OUT",
    "t_status": "SUCCESSFUL",
    "t_timestamp": "2024-02-07T19:47:58.576Z",
    "client_transaction_id": "85CD5149-84DA-45A1-883D-EDC0BB1A2DB9-274-000000D7AA03E3E7",
    "fee_amount": 0.04,
    "t_card": "MASTERCARD",
    "refunded_amount": 0
  },
  {
    "id": "1eec5f25-6389-6740-a319-037ac15e1623",
    "transaction_code": "TE6MKY2A4A",
    "status": "SUCCESSFUL",
    "timestamp": "2024-02-07T19:51:51.470Z",
    "type": "PAYMENT",
    "amount": 8.94,
    "simple_status": "PAID_OUT",
    "t_status": "SUCCESSFUL",
    "t_timestamp": "2024-02-07T19:51:51.470Z",
    "client_transaction_id": "BE586AE3-74F9-45A8-A205-FABD57238230-274-000000D8F731392C",
    "fee_amount": 0.09,
    "t_card": "MASTERCARD",
    "refunded_amount": 0
  },
  {
    "id": "1eec5f29-0ad9-6434-bb99-a03b074bfa96",
    "transaction_code": "TC7UEFMEAN",
    "status": "SUCCESSFUL",
    "timestamp": "2024-02-07T19:53:29.554Z",
    "type": "PAYMENT",
    "amount": 7.24,
    "simple_status": "PAID_OUT",
    "t_status": "SUCCESSFUL",
    "t_timestamp": "2024-02-07T19:53:29.554Z",
    "client_transaction_id": "E3A166D5-5D8E-43FA-AEDC-5B2D3605E578-274-000000D983874E94",
    "fee_amount": 0.07,
    "t_card": "VISA",
    "refunded_amount": 0
  },
  {
    "id": "1eec5f2b-621d-6db7-aba4-9b6e80b102db",
    "transaction_code": "TEQXX27CZS",
    "status": "SUCCESSFUL",
    "timestamp": "2024-02-07T19:54:32.391Z",
    "type": "PAYMENT",
    "amount": 4.33,
    "simple_status": "PAID_OUT",
    "t_status": "SUCCESSFUL",
    "t_timestamp": "2024-02-07T19:54:32.391Z",
    "client_transaction_id": "8A25A3B0-9782-40E3-9D5B-59B03AED353E-274-000000D9DD5E3989",
    "fee_amount": 0.04,
    "t_card": "VISA",
    "refunded_amount": 0
  },
  {
    "id": "1eec5f35-7dba-6834-8249-d33b56af64ba",
    "transaction_code": "TEXA7KL64Y",
    "status": "SUCCESSFUL",
    "timestamp": "2024-02-07T19:59:03.713Z",
    "type": "PAYMENT",
    "amount": 4.38,
    "simple_status": "PAID_OUT",
    "t_status": "SUCCESSFUL",
    "t_timestamp": "2024-02-07T19:59:03.713Z",
    "client_transaction_id": "B06F3250-F9F0-41B7-9821-C503BB714B99-274-000000DB618C7A91",
    "fee_amount": 0.04,
    "t_card": "VISA",
    "refunded_amount": 0
  },
  {
    "id": "1eec5f38-92d3-6600-b2ef-efe5a6ad452f",
    "transaction_code": "TCEGX9SATR",
    "status": "SUCCESSFUL",
    "timestamp": "2024-02-07T20:00:26.453Z",
    "type": "PAYMENT",
    "amount": 8.59,
    "simple_status": "PAID_OUT",
    "t_status": "SUCCESSFUL",
    "t_timestamp": "2024-02-07T20:00:26.453Z",
    "client_transaction_id": "95FA05C4-DFB3-4AB9-AA6D-3AA63B9C151F-274-000000DBD7CAE5DF",
    "fee_amount": 0.09,
    "t_card": "VISA",
    "refunded_amount": 0
  },
  {
    "id": "1eec5f3b-617f-68a8-b510-5fc16b9847a5",
    "transaction_code": "TFETVYLNAP",
    "status": "SUCCESSFUL",
    "timestamp": "2024-02-07T20:01:41.826Z",
    "type": "PAYMENT",
    "amount": 12.06,
    "simple_status": "PAID_OUT",
    "t_status": "SUCCESSFUL",
    "t_timestamp": "2024-02-07T20:01:41.826Z",
    "client_transaction_id": "B3F1DFBB-978A-4FE1-8E59-1F140BF49768-274-000000DC43C1BDC7",
    "fee_amount": 0.12,
    "t_card": "VISA",
    "refunded_amount": 0
  },
  {
    "id": "1eec5f40-150e-6cc0-a2ae-e4bd83425409",
    "transaction_code": "TFRGF4YKYV",
    "status": "SUCCESSFUL",
    "timestamp": "2024-02-07T20:03:48.016Z",
    "type": "PAYMENT",
    "amount": 7.47,
    "simple_status": "PAID_OUT",
    "t_status": "SUCCESSFUL",
    "t_timestamp": "2024-02-07T20:03:48.016Z",
    "client_transaction_id": "4AE25F8C-7E1E-4929-868D-627F51BB82AA-274-000000DCF843CDD8",
    "fee_amount": 0.07,
    "t_card": "MASTERCARD",
    "refunded_amount": 0
  },
  {
    "id": "1eec5f41-3783-6644-98d0-5b4d146c103d",
    "transaction_code": "TDPFTZKLP4",
    "status": "SUCCESSFUL",
    "timestamp": "2024-02-07T20:04:18.478Z",
    "type": "PAYMENT",
    "amount": 3.49,
    "simple_status": "PAID_OUT",
    "t_status": "SUCCESSFUL",
    "t_timestamp": "2024-02-07T20:04:18.478Z",
    "client_transaction_id": "B074C4CF-480E-4C21-9C22-ED48DE1D5381-274-000000DD23F6DA54",
    "fee_amount": 0.03,
    "t_card": "MASTERCARD",
    "refunded_amount": 0
  },
  {
    "id": "1eec5f45-29ba-6879-ad92-4b2cd6cd0122",
    "transaction_code": "TFQGXZXNKX",
    "status": "SUCCESSFUL",
    "timestamp": "2024-02-07T20:06:04.402Z",
    "type": "PAYMENT",
    "amount": 6.79,
    "simple_status": "PAID_OUT",
    "t_status": "SUCCESSFUL",
    "t_timestamp": "2024-02-07T20:06:04.402Z",
    "client_transaction_id": "C5A9F289-3F4F-4863-B288-67B0A2B3B08B-274-000000DDBB5C7134",
    "fee_amount": 0.07,
    "t_card": "VISA",
    "refunded_amount": 0
  },
  {
    "id": "1eec5f53-24d5-6646-9884-7a270e56e12f",
    "transaction_code": "TFLEKZFM4Z",
    "status": "SUCCESSFUL",
    "timestamp": "2024-02-07T20:12:19.703Z",
    "type": "PAYMENT",
    "amount": 20.27,
    "simple_status": "PAID_OUT",
    "t_status": "SUCCESSFUL",
    "t_timestamp": "2024-02-07T20:12:19.703Z",
    "client_transaction_id": "E9A214E3-7C8A-4F5E-91D1-07D2AF8B4D8E-274-000000DFD4419C95",
    "fee_amount": 0.2,
    "t_card": "VISA",
    "refunded_amount": 0
  },
  {
    "id": "1eec5f59-1fb7-60a4-944c-f3c66d7ff76c",
    "transaction_code": "TDFMVRPTRX",
    "status": "SUCCESSFUL",
    "timestamp": "2024-02-07T20:15:00.229Z",
    "type": "PAYMENT",
    "amount": 7.24,
    "simple_status": "PAID_OUT",
    "t_status": "SUCCESSFUL",
    "t_timestamp": "2024-02-07T20:15:00.229Z",
    "client_transaction_id": "9B4945A2-7F6F-4159-8005-2E505310B186-274-000000E0B9F6081A",
    "fee_amount": 0.07,
    "t_card": "VISA",
    "refunded_amount": 0
  },
  {
    "id": "1eec5f5e-f638-6c44-9dd0-fc881348ebfe",
    "transaction_code": "TC3D7QYPCA",
    "status": "SUCCESSFUL",
    "timestamp": "2024-02-07T20:17:36.951Z",
    "type": "PAYMENT",
    "amount": 4.21,
    "simple_status": "PAID_OUT",
    "t_status": "SUCCESSFUL",
    "t_timestamp": "2024-02-07T20:17:36.951Z",
    "client_transaction_id": "2ED0DACA-C7E1-47C5-9C6A-1F4DABA3496A-274-000000E199E96006",
    "fee_amount": 0.04,
    "t_card": "VISA",
    "refunded_amount": 0
  },
  {
    "id": "1eec5f66-ee0d-6977-9077-3ce8b2ee57f3",
    "transaction_code": "TERXPHQNZ4",
    "status": "SUCCESSFUL",
    "timestamp": "2024-02-07T20:21:10.826Z",
    "type": "PAYMENT",
    "amount": 6,
    "simple_status": "PAID_OUT",
    "t_status": "SUCCESSFUL",
    "t_timestamp": "2024-02-07T20:21:10.826Z",
    "client_transaction_id": "D740A0D6-4490-4EA9-9F67-445BC16E1CF4-274-000000E2CC1FF09A",
    "fee_amount": 0.06,
    "t_card": "VISA",
    "refunded_amount": 0
  },
  {
    "id": "1eec5f6a-9c70-6ce7-9cb2-4a4c25cf7fa3",
    "transaction_code": "TDVAGUENH9",
    "status": "SUCCESSFUL",
    "timestamp": "2024-02-07T20:22:49.636Z",
    "type": "PAYMENT",
    "amount": 4.38,
    "simple_status": "PAID_OUT",
    "t_status": "SUCCESSFUL",
    "t_timestamp": "2024-02-07T20:22:49.636Z",
    "client_transaction_id": "1F35D9AF-6AAD-4237-9FDA-3F91633B7D37-274-000000E35976E46D",
    "fee_amount": 0.04,
    "t_card": "VISA",
    "refunded_amount": 0
  },
  {
    "id": "1eec5f72-87a4-6a6d-8d09-e7835487fcfe",
    "transaction_code": "TFXNQ4LEH2",
    "status": "SUCCESSFUL",
    "timestamp": "2024-02-07T20:26:22.210Z",
    "type": "PAYMENT",
    "amount": 7.49,
    "simple_status": "PAID_OUT",
    "t_status": "SUCCESSFUL",
    "t_timestamp": "2024-02-07T20:26:22.210Z",
    "client_transaction_id": "87A2BA28-8C86-427C-AE81-E87390D3F37B-274-000000E48998E827",
    "fee_amount": 0.07,
    "t_card": "MASTERCARD",
    "refunded_amount": 0
  },
  {
    "id": "1eec5f74-d9d4-6c25-973b-8e19c194fff8",
    "transaction_code": "TYM42V6XFX",
    "status": "SUCCESSFUL",
    "timestamp": "2024-02-07T20:27:24.515Z",
    "type": "PAYMENT",
    "amount": 6.65,
    "simple_status": "PAID_OUT",
    "t_status": "SUCCESSFUL",
    "t_timestamp": "2024-02-07T20:27:24.515Z",
    "client_transaction_id": "DDB6205C-DC7B-4B33-88B1-AF8B1630DDBD-274-000000E4E2B03080",
    "fee_amount": 0.07,
    "t_card": "MASTERCARD",
    "refunded_amount": 0
  },
  {
    "id": "1eec5f7a-2ced-6526-86fc-e893ed7ca448",
    "transaction_code": "TFC24XV44F",
    "status": "SUCCESSFUL",
    "timestamp": "2024-02-07T20:29:47.451Z",
    "type": "PAYMENT",
    "amount": 7.94,
    "simple_status": "PAID_OUT",
    "t_status": "SUCCESSFUL",
    "t_timestamp": "2024-02-07T20:29:47.451Z",
    "client_transaction_id": "CC84A6BF-1260-40A3-83A9-3AFECAF83261-274-000000E5AF2742AA",
    "fee_amount": 0.08,
    "t_card": "MASTERCARD",
    "refunded_amount": 0
  },
  {
    "id": "1eec5f8f-b948-622a-8b65-23c6f318e818",
    "transaction_code": "T4LFM2DEY4",
    "status": "SUCCESSFUL",
    "timestamp": "2024-02-07T20:39:25.878Z",
    "type": "PAYMENT",
    "amount": 11.35,
    "simple_status": "PAID_OUT",
    "t_status": "SUCCESSFUL",
    "t_timestamp": "2024-02-07T20:39:25.878Z",
    "client_transaction_id": "E41A9C6A-FF3D-41B7-B010-261B25A07209-274-000000E8EA96C221",
    "fee_amount": 0.11,
    "t_card": "MASTERCARD",
    "refunded_amount": 0
  },
  {
    "id": "1eec5f90-cfc0-61c9-8b80-bd7bc0e2ebac",
    "transaction_code": "TEXZHSNYVU",
    "status": "SUCCESSFUL",
    "timestamp": "2024-02-07T20:39:55.080Z",
    "type": "PAYMENT",
    "amount": 4.21,
    "simple_status": "PAID_OUT",
    "t_status": "SUCCESSFUL",
    "t_timestamp": "2024-02-07T20:39:55.080Z",
    "client_transaction_id": "9081C606-83AD-4E3D-A9EC-CBBA8E7B4D77-274-000000E91487DF6E",
    "fee_amount": 0.04,
    "t_card": "MASTERCARD",
    "refunded_amount": 0
  },
  {
    "id": "1eec5f94-57cc-6555-97f0-a560cc159693",
    "transaction_code": "TERPHY7PUU",
    "status": "SUCCESSFUL",
    "timestamp": "2024-02-07T20:41:29.889Z",
    "type": "PAYMENT",
    "amount": 5.47,
    "simple_status": "PAID_OUT",
    "t_status": "SUCCESSFUL",
    "t_timestamp": "2024-02-07T20:41:29.889Z",
    "client_transaction_id": "1B3009C0-3184-40ED-9561-44C7F883FF86-274-000000E99C135D20",
    "fee_amount": 0.05,
    "t_card": "VISA",
    "refunded_amount": 0
  },
  {
    "id": "1eec5f97-d502-68b9-9057-42dacf2d0a4e",
    "transaction_code": "TFGG9AYF4K",
    "status": "SUCCESSFUL",
    "timestamp": "2024-02-07T20:43:03.538Z",
    "type": "PAYMENT",
    "amount": 7.48,
    "simple_status": "PAID_OUT",
    "t_status": "SUCCESSFUL",
    "t_timestamp": "2024-02-07T20:43:03.538Z",
    "client_transaction_id": "B3992A80-1BF9-492D-9026-9CFBCD763FF1-274-000000EA220DCB64",
    "fee_amount": 0.07,
    "t_card": "VISA",
    "refunded_amount": 0
  },
  {
    "id": "1eec5f9e-f21f-664f-9060-2023cf59bcbc",
    "transaction_code": "TECLQ2GV9Z",
    "status": "SUCCESSFUL",
    "timestamp": "2024-02-07T20:46:14.489Z",
    "type": "PAYMENT",
    "amount": 14.96,
    "simple_status": "PAID_OUT",
    "t_status": "SUCCESSFUL",
    "t_timestamp": "2024-02-07T20:46:14.489Z",
    "client_transaction_id": "3F0A0FD7-26C7-41FD-83D2-E59B71EF5AC0-274-000000EB3348FD1B",
    "fee_amount": 0.15,
    "t_card": "MASTERCARD",
    "refunded_amount": 0
  },
  {
    "id": "1eec5fb0-edc4-60af-83c2-f2742a82bda2",
    "transaction_code": "TDVEF7S2A6",
    "status": "SUCCESSFUL",
    "timestamp": "2024-02-07T20:54:17.228Z",
    "type": "PAYMENT",
    "amount": 10.9,
    "simple_status": "PAID_OUT",
    "t_status": "SUCCESSFUL",
    "t_timestamp": "2024-02-07T20:54:17.228Z",
    "client_transaction_id": "37E3B2AC-C414-43D0-A849-83A614408FC9-274-000000EDE5B7C6D4",
    "fee_amount": 0.11,
    "t_card": "VISA",
    "refunded_amount": 0
  },
  {
    "id": "1eec5fb2-c953-6a32-8460-b07fa8aff57d",
    "transaction_code": "TDQ3LH9SYZ",
    "status": "SUCCESSFUL",
    "timestamp": "2024-02-07T20:55:07.091Z",
    "type": "PAYMENT",
    "amount": 7.75,
    "simple_status": "PAID_OUT",
    "t_status": "SUCCESSFUL",
    "t_timestamp": "2024-02-07T20:55:07.091Z",
    "client_transaction_id": "7EC85A12-A7ED-4EF5-B84B-F7357BD33E9A-274-000000EE2D2B3F44",
    "fee_amount": 0.08,
    "t_card": "MASTERCARD",
    "refunded_amount": 0
  },
  {
    "id": "1eec5fb8-9d31-6e88-9aab-6e8db95d3c8d",
    "transaction_code": "TE4AN6T2EY",
    "status": "SUCCESSFUL",
    "timestamp": "2024-02-07T20:57:43.523Z",
    "type": "PAYMENT",
    "amount": 3.27,
    "simple_status": "PAID_OUT",
    "t_status": "SUCCESSFUL",
    "t_timestamp": "2024-02-07T20:57:43.523Z",
    "client_transaction_id": "8CB6E5B3-FAD1-4047-814A-4C8BAE143C5D-274-000000EF0CF178BA",
    "fee_amount": 0.03,
    "t_card": "VISA",
    "refunded_amount": 0
  },
  {
    "id": "1eec5fc1-13b0-6d84-bec8-9cd45f74cd41",
    "transaction_code": "TCPLSY2VAP",
    "status": "SUCCESSFUL",
    "timestamp": "2024-02-07T21:01:30.693Z",
    "type": "PAYMENT",
    "amount": 4.21,
    "simple_status": "PAID_OUT",
    "t_status": "SUCCESSFUL",
    "t_timestamp": "2024-02-07T21:01:30.693Z",
    "client_transaction_id": "3F3A1DB4-2C49-4316-86CB-DAA7C341CCF7-274-000000F051ED11EF",
    "fee_amount": 0.04,
    "t_card": "VISA",
    "refunded_amount": 0
  },
  {
    "id": "1eec5fcf-d19a-6eb8-8d36-30134d30b7ca",
    "transaction_code": "TM4LXMRYFH",
    "status": "SUCCESSFUL",
    "timestamp": "2024-02-07T21:08:06.419Z",
    "type": "PAYMENT",
    "amount": 12.74,
    "simple_status": "PAID_OUT",
    "t_status": "SUCCESSFUL",
    "t_timestamp": "2024-02-07T21:08:06.419Z",
    "client_transaction_id": "5265D0D7-9E93-4B39-9BA4-556742A3D94D-274-000000F28821A1E6",
    "fee_amount": 0.13,
    "t_card": "VISA",
    "refunded_amount": 0
  },
  {
    "id": "1eec600d-842a-6265-83a4-275cc2c53d95",
    "transaction_code": "TERKV4L9Y6",
    "status": "SUCCESSFUL",
    "timestamp": "2024-02-07T21:35:42.610Z",
    "type": "PAYMENT",
    "amount": 14.48,
    "simple_status": "PAID_OUT",
    "t_status": "SUCCESSFUL",
    "t_timestamp": "2024-02-07T21:35:42.610Z",
    "client_transaction_id": "C46F43DE-AC91-4720-BF59-6AEBC44CFDB0-274-000000FBC94CA1FF",
    "fee_amount": 0.14,
    "t_card": "VISA",
    "refunded_amount": 0
  },
  {
    "id": "1eec6010-9cbd-6bb8-8361-89cbd015a51d",
    "transaction_code": "TCUYDV9VSK",
    "status": "SUCCESSFUL",
    "timestamp": "2024-02-07T21:37:05.706Z",
    "type": "PAYMENT",
    "amount": 8.8,
    "simple_status": "PAID_OUT",
    "t_status": "SUCCESSFUL",
    "t_timestamp": "2024-02-07T21:37:05.706Z",
    "client_transaction_id": "3E8C42A4-39B8-43D0-8D4E-B9B930B6A0F7-274-000000FC403F3D76",
    "fee_amount": 0.09,
    "t_card": "VISA",
    "refunded_amount": 0
  },
  {
    "id": "1eec6024-8d1c-6874-b1c7-0d050d284f7b",
    "transaction_code": "TD92GM9VS4",
    "status": "SUCCESSFUL",
    "timestamp": "2024-02-07T21:46:00.948Z",
    "type": "PAYMENT",
    "amount": 5.15,
    "simple_status": "PAID_OUT",
    "t_status": "SUCCESSFUL",
    "t_timestamp": "2024-02-07T21:46:00.948Z",
    "client_transaction_id": "E570D761-1285-43C9-9B87-5E5E44DB0FEF-274-000000FF3DE39384",
    "fee_amount": 0.05,
    "t_card": "VISA",
    "refunded_amount": 0
  }
]